{
  "time": "2025-09-02 11:36:19",
  "dataset": "ag_news",
  "config": {
    "rank": 0,
    "world_size": 6,
    "iface": "ens4f0",
    "master_addr": "42.0.0.1",
    "master_port": 29500,
    "backend": "gloo",
    "device": "cuda",
    "deterministic": true,
    "workers": 8,
    "json": "/home/gks/straggle-ml-experiments/models/lstm_classify.json",
    "dataset": "ag_news",
    "epochs": 25,
    "batch_size": 64,
    "learning_rate": 0.001,
    "weight_decay": 1e-05,
    "step_size": 5,
    "gamma": 0.5,
    "amp": false,
    "drop_last_train": false,
    "drop_last_val": true,
    "static_graph": false,
    "prefetch_factor": 2,
    "embed_dim": 256,
    "hidden_dim": 512,
    "num_layers": 2,
    "dropout": 0.3,
    "max_len": 128,
    "max_vocab": 20000,
    "bidirectional": false,
    "num_classes": 4,
    "local_rank": 0,
    "seed": 42
  },
  "vocab_size": 20000,
  "epochs": {
    "0": {
      "train_loss": 0.6056043202400208,
      "train_loss_global": 0.6131197053829829,
      "train_acc": 77.21,
      "train_acc_global": 76.83666666666667,
      "train_step_time": 0.09986970852205036,
      "train_data_time": 0.0005911507404977664,
      "train_comp_time": 0.09927855778155259,
      "train_duration": 31.26038671875,
      "train_throughput": 639.787350679318,
      "val_loss": 0.3868945922898619,
      "val_acc": 86.92105263157895,
      "lr": 0.001,
      "epoch_time": 31.83103895187378,
      "epoch_throughput": 3769.905223057007,
      "steps": 313
    },
    "1": {
      "train_loss": 0.3555429407119751,
      "train_loss_global": 0.3569174429655075,
      "train_acc": 87.955,
      "train_acc_global": 87.91333333333333,
      "train_step_time": 0.09841995039759888,
      "train_data_time": 0.00030243158460960696,
      "train_comp_time": 0.09811751881298927,
      "train_duration": 30.80641015625,
      "train_throughput": 649.2155333438747,
      "val_loss": 0.36079364340556297,
      "val_acc": 88.78947368421052,
      "lr": 0.001,
      "epoch_time": 31.204985857009888,
      "epoch_throughput": 3845.5393170140856,
      "steps": 313
    },
    "2": {
      "train_loss": 0.30415817790031435,
      "train_loss_global": 0.30522053323586784,
      "train_acc": 89.86,
      "train_acc_global": 89.7275,
      "train_step_time": 0.09747139537244286,
      "train_data_time": 0.0003381042124572606,
      "train_comp_time": 0.09713329115998559,
      "train_duration": 30.50951953125,
      "train_throughput": 655.5331026932296,
      "val_loss": 0.3181564902984782,
      "val_acc": 90.09210526315789,
      "lr": 0.001,
      "epoch_time": 30.927425622940063,
      "epoch_throughput": 3880.0513648634037,
      "steps": 313
    },
    "3": {
      "train_loss": 0.26770946433544157,
      "train_loss_global": 0.268964453903834,
      "train_acc": 91.09,
      "train_acc_global": 91.0075,
      "train_step_time": 0.09749610488453267,
      "train_data_time": 0.000384050060640842,
      "train_comp_time": 0.09711205482389183,
      "train_duration": 30.517244140625,
      "train_throughput": 655.3671723383341,
      "val_loss": 0.30331744655182485,
      "val_acc": 90.30263157894737,
      "lr": 0.001,
      "epoch_time": 30.926597833633423,
      "epoch_throughput": 3880.155219320539,
      "steps": 313
    },
    "4": {
      "train_loss": 0.24713521161079408,
      "train_loss_global": 0.24620042887528737,
      "train_acc": 91.56,
      "train_acc_global": 91.70666666666666,
      "train_step_time": 0.09785004609268896,
      "train_data_time": 0.00029664979570697005,
      "train_comp_time": 0.097553396296982,
      "train_duration": 30.6280546875,
      "train_throughput": 652.9960914612853,
      "val_loss": 0.2851905380640375,
      "val_acc": 90.60526315789474,
      "lr": 0.001,
      "epoch_time": 31.0287926197052,
      "epoch_throughput": 3867.3757458352597,
      "steps": 313
    },
    "5": {
      "train_loss": 0.19934602046012878,
      "train_loss_global": 0.20082088872989018,
      "train_acc": 93.425,
      "train_acc_global": 93.17666666666666,
      "train_step_time": 0.09692082769563273,
      "train_data_time": 0.00032094089588084924,
      "train_comp_time": 0.09659988679975189,
      "train_duration": 30.337203125,
      "train_throughput": 659.2565543235127,
      "val_loss": 0.27874277765029354,
      "val_acc": 91.15789473684211,
      "lr": 0.0005,
      "epoch_time": 30.745304822921753,
      "epoch_throughput": 3903.0349736697226,
      "steps": 313
    },
    "6": {
      "train_loss": 0.19358387688398362,
      "train_loss_global": 0.18691278178890547,
      "train_acc": 93.385,
      "train_acc_global": 93.62583333333333,
      "train_step_time": 0.09753892152977828,
      "train_data_time": 0.0003821583436474728,
      "train_comp_time": 0.0971567631861308,
      "train_duration": 30.5306796875,
      "train_throughput": 655.078766824457,
      "val_loss": 0.262425682191786,
      "val_acc": 91.61842105263158,
      "lr": 0.0005,
      "epoch_time": 30.932169914245605,
      "epoch_throughput": 3879.4562532366926,
      "steps": 313
    },
    "7": {
      "train_loss": 0.17279925278425218,
      "train_loss_global": 0.17318213512599467,
      "train_acc": 93.92,
      "train_acc_global": 94.05166666666666,
      "train_step_time": 0.09792257784144245,
      "train_data_time": 0.00040327208027386436,
      "train_comp_time": 0.09751930576116859,
      "train_duration": 30.650798828125,
      "train_throughput": 652.5115417758088,
      "val_loss": 0.26882020625432856,
      "val_acc": 91.57894736842105,
      "lr": 0.0005,
      "epoch_time": 31.043229579925537,
      "epoch_throughput": 3865.577184585182,
      "steps": 313
    },
    "8": {
      "train_loss": 0.15175461724996567,
      "train_loss_global": 0.1582744485169649,
      "train_acc": 94.665,
      "train_acc_global": 94.52333333333333,
      "train_step_time": 0.09736338922993455,
      "train_data_time": 0.0003029161159651348,
      "train_comp_time": 0.09706047311396941,
      "train_duration": 30.4756875,
      "train_throughput": 656.2608308672282,
      "val_loss": 0.2681629594905596,
      "val_acc": 91.52631578947368,
      "lr": 0.0005,
      "epoch_time": 30.89169478416443,
      "epoch_throughput": 3884.539221250946,
      "steps": 313
    },
    "9": {
      "train_loss": 0.14823299868106843,
      "train_loss_global": 0.14642679045796395,
      "train_acc": 94.885,
      "train_acc_global": 94.92666666666666,
      "train_step_time": 0.09744139669125322,
      "train_data_time": 0.00037882412254167634,
      "train_comp_time": 0.09706257256871155,
      "train_duration": 30.50010546875,
      "train_throughput": 655.7354373902651,
      "val_loss": 0.2670547193220179,
      "val_acc": 91.78947368421052,
      "lr": 0.0005,
      "epoch_time": 30.90564274787903,
      "epoch_throughput": 3882.7860976369852,
      "steps": 313
    },
    "10": {
      "train_loss": 0.12197027388811112,
      "train_loss_global": 0.12122558871706327,
      "train_acc": 95.745,
      "train_acc_global": 95.79083333333334,
      "train_step_time": 0.0979594744863911,
      "train_data_time": 0.0003839677691417999,
      "train_comp_time": 0.0975755067172493,
      "train_duration": 30.662271484375,
      "train_throughput": 652.2673967645117,
      "val_loss": 0.27982106782005806,
      "val_acc": 91.88157894736842,
      "lr": 0.00025,
      "epoch_time": 31.07243514060974,
      "epoch_throughput": 3861.9438565716873,
      "steps": 313
    },
    "11": {
      "train_loss": 0.11213892658948899,
      "train_loss_global": 0.1115030789365371,
      "train_acc": 96.03,
      "train_acc_global": 96.09583333333333,
      "train_step_time": 0.09697973990839677,
      "train_data_time": 0.0003771432697737274,
      "train_comp_time": 0.09660259663862304,
      "train_duration": 30.35563671875,
      "train_throughput": 658.8562178847808,
      "val_loss": 0.2798700892523323,
      "val_acc": 92.10526315789474,
      "lr": 0.00025,
      "epoch_time": 30.7687566280365,
      "epoch_throughput": 3900.060098322464,
      "steps": 313
    },
    "12": {
      "train_loss": 0.09950652350187301,
      "train_loss_global": 0.10409875707129637,
      "train_acc": 96.46,
      "train_acc_global": 96.265,
      "train_step_time": 0.09789890849690575,
      "train_data_time": 0.0004074370667796594,
      "train_comp_time": 0.09749147143012608,
      "train_duration": 30.643326171875,
      "train_throughput": 652.6706627022872,
      "val_loss": 0.2999638650350665,
      "val_acc": 91.98684210526316,
      "lr": 0.00025,
      "epoch_time": 31.06656765937805,
      "epoch_throughput": 3862.673254274862,
      "steps": 313
    },
    "13": {
      "train_loss": 0.09404199513792992,
      "train_loss_global": 0.09461040450334549,
      "train_acc": 96.905,
      "train_acc_global": 96.67416666666666,
      "train_step_time": 0.09784076784063464,
      "train_data_time": 0.000340612714562696,
      "train_comp_time": 0.09750015512607195,
      "train_duration": 30.62515234375,
      "train_throughput": 653.0579758595588,
      "val_loss": 0.3387995311529621,
      "val_acc": 91.60526315789474,
      "lr": 0.00025,
      "epoch_time": 31.02303433418274,
      "epoch_throughput": 3868.0935819285082,
      "steps": 313
    },
    "14": {
      "train_loss": 0.08699252596497535,
      "train_loss_global": 0.08974051153063774,
      "train_acc": 96.895,
      "train_acc_global": 96.79416666666667,
      "train_step_time": 0.09662035736106574,
      "train_data_time": 0.00030986706320101177,
      "train_comp_time": 0.09631049029786473,
      "train_duration": 30.24310546875,
      "train_throughput": 661.3077489897943,
      "val_loss": 0.31032154238145604,
      "val_acc": 91.90789473684211,
      "lr": 0.00025,
      "epoch_time": 30.653522491455078,
      "epoch_throughput": 3914.721384253669,
      "steps": 313
    },
    "15": {
      "train_loss": 0.07594635376930237,
      "train_loss_global": 0.07547288811703523,
      "train_acc": 97.31,
      "train_acc_global": 97.32583333333334,
      "train_step_time": 0.0979705849207176,
      "train_data_time": 0.00029626683021089233,
      "train_comp_time": 0.09767431809050671,
      "train_duration": 30.665755859375,
      "train_throughput": 652.1932833390665,
      "val_loss": 0.34107839613368635,
      "val_acc": 92.0,
      "lr": 0.000125,
      "epoch_time": 31.07194209098816,
      "epoch_throughput": 3862.005137902332,
      "steps": 313
    },
    "16": {
      "train_loss": 0.07363651107549668,
      "train_loss_global": 0.06969622587462267,
      "train_acc": 97.395,
      "train_acc_global": 97.4975,
      "train_step_time": 0.0982363900064101,
      "train_data_time": 0.0004125091685398747,
      "train_comp_time": 0.09782388083787023,
      "train_duration": 30.748931640625,
      "train_throughput": 650.4291021798077,
      "val_loss": 0.3460418636567498,
      "val_acc": 91.96052631578948,
      "lr": 0.000125,
      "epoch_time": 31.168115854263306,
      "epoch_throughput": 3850.0883582793117,
      "steps": 313
    },
    "17": {
      "train_loss": 0.06647750017046929,
      "train_loss_global": 0.06637374796668688,
      "train_acc": 97.64,
      "train_acc_global": 97.65666666666667,
      "train_step_time": 0.09729301321808213,
      "train_data_time": 0.0003641796601079285,
      "train_comp_time": 0.0969288335579742,
      "train_duration": 30.45367578125,
      "train_throughput": 656.7351719267264,
      "val_loss": 0.36064702135167626,
      "val_acc": 91.69736842105263,
      "lr": 0.000125,
      "epoch_time": 30.859192371368408,
      "epoch_throughput": 3888.6306082118235,
      "steps": 313
    },
    "18": {
      "train_loss": 0.06633886296749116,
      "train_loss_global": 0.0639722509175539,
      "train_acc": 97.635,
      "train_acc_global": 97.6825,
      "train_step_time": 0.09794641400690372,
      "train_data_time": 0.00039412429966865635,
      "train_comp_time": 0.09755228970723506,
      "train_duration": 30.6581953125,
      "train_throughput": 652.3541192212829,
      "val_loss": 0.3594520628550335,
      "val_acc": 92.0657894736842,
      "lr": 0.000125,
      "epoch_time": 31.054670333862305,
      "epoch_throughput": 3864.1530793888633,
      "steps": 313
    },
    "19": {
      "train_loss": 0.06271718416810036,
      "train_loss_global": 0.06101794267892838,
      "train_acc": 97.82,
      "train_acc_global": 97.79583333333333,
      "train_step_time": 0.09864297925722235,
      "train_data_time": 0.00031953036990433264,
      "train_comp_time": 0.09832344888731802,
      "train_duration": 30.87619140625,
      "train_throughput": 647.748284004729,
      "val_loss": 0.3652737969473789,
      "val_acc": 91.73684210526316,
      "lr": 0.000125,
      "epoch_time": 31.29246187210083,
      "epoch_throughput": 3834.789365262036,
      "steps": 313
    },
    "20": {
      "train_loss": 0.050946167784929275,
      "train_loss_global": 0.05287521778444449,
      "train_acc": 98.145,
      "train_acc_global": 98.09,
      "train_step_time": 0.09710684073114464,
      "train_data_time": 0.00035178238680711187,
      "train_comp_time": 0.09675505834433754,
      "train_duration": 30.395392578125,
      "train_throughput": 657.9944624368375,
      "val_loss": 0.37859926019893275,
      "val_acc": 91.89473684210526,
      "lr": 6.25e-05,
      "epoch_time": 30.799556016921997,
      "epoch_throughput": 3896.1600593875182,
      "steps": 313
    },
    "21": {
      "train_loss": 0.050014103257656095,
      "train_loss_global": 0.04973454740941524,
      "train_acc": 98.19,
      "train_acc_global": 98.16916666666667,
      "train_step_time": 0.09797283851566871,
      "train_data_time": 0.00034350873835491965,
      "train_comp_time": 0.09762932977731378,
      "train_duration": 30.66645703125,
      "train_throughput": 652.1783712940633,
      "val_loss": 0.39204784566414,
      "val_acc": 91.80263157894737,
      "lr": 6.25e-05,
      "epoch_time": 31.068756103515625,
      "epoch_throughput": 3862.401172424835,
      "steps": 313
    },
    "22": {
      "train_loss": 0.05084066305756569,
      "train_loss_global": 0.04791966866155466,
      "train_acc": 98.055,
      "train_acc_global": 98.22416666666666,
      "train_step_time": 0.09788269479201137,
      "train_data_time": 0.0003824247681080533,
      "train_comp_time": 0.09750027002390331,
      "train_duration": 30.63824609375,
      "train_throughput": 652.7788809712534,
      "val_loss": 0.3859966860123371,
      "val_acc": 91.96052631578948,
      "lr": 6.25e-05,
      "epoch_time": 31.044684410095215,
      "epoch_throughput": 3865.3960341429015,
      "steps": 313
    },
    "23": {
      "train_loss": 0.04680401862859726,
      "train_loss_global": 0.04623487003942331,
      "train_acc": 98.335,
      "train_acc_global": 98.38833333333334,
      "train_step_time": 0.0974295869489727,
      "train_data_time": 0.00039432706614843193,
      "train_comp_time": 0.09703525988282427,
      "train_duration": 30.496447265625,
      "train_throughput": 655.8140961732158,
      "val_loss": 0.4033907354493184,
      "val_acc": 91.85526315789474,
      "lr": 6.25e-05,
      "epoch_time": 30.884628772735596,
      "epoch_throughput": 3885.427954566638,
      "steps": 313
    },
    "24": {
      "train_loss": 0.04662116910815239,
      "train_loss_global": 0.046661348581314085,
      "train_acc": 98.265,
      "train_acc_global": 98.32833333333333,
      "train_step_time": 0.0980078698289893,
      "train_data_time": 0.00037641618504953653,
      "train_comp_time": 0.09763145364393977,
      "train_duration": 30.6774609375,
      "train_throughput": 651.9444370166921,
      "val_loss": 0.400606609845632,
      "val_acc": 92.05263157894737,
      "lr": 6.25e-05,
      "epoch_time": 31.078826189041138,
      "epoch_throughput": 3861.149686609265,
      "steps": 313
    }
  }
}